#######################################################################################################################################
<poster>petermesh</poster>
<fanart>http://rockbanddlc.org/images/jamesmay/fan_James_May%27s_Lego_House_nears_completion.jpg</fanart>
#######################################################################################################################################
<item>
<title>S01E01 - Airfix</title>
<thumbnail>http://rockbanddlc.org/images/jamesmay/thumb_JMTStitle.png</thumbnail>
<fanart>http://rockbanddlc.org/images/jamesmay/fan_James_May%27s_Lego_House_nears_completion.jpg</fanart>
<link>
<sublink>http://www.sockshare.com/file/3485E035915989D4</sublink>
<sublink>http://www.firedrive.com/file/DF016432902F72A5</sublink>
<sublink>http://rapidgator.net/file/5a62500263cd45980cef8473cdc656f0/James.Mays.Toy.Stories.S01E01.Airfix.DVDRip.XviD-aAF.avi.html</sublink>
</link>
</item>